napari_blender_bridge/__init__.py
napari_blender_bridge/_blender_server.py
napari_blender_bridge/_function.py
napari_blender_bridge/_public_api.py
napari_blender_bridge/_tests/__init__.py
napari_blender_bridge/_tests/test_function.py
napari_blender_bridge-0.2.0.dist-info/LICENSE
napari_blender_bridge-0.2.0.dist-info/METADATA
napari_blender_bridge-0.2.0.dist-info/WHEEL
napari_blender_bridge-0.2.0.dist-info/entry_points.txt
napari_blender_bridge-0.2.0.dist-info/top_level.txt
napari_blender_bridge-0.2.0.dist-info/RECORD
