Metadata-Version: 2.1
Name: napari-blender-bridge
Version: 0.2.0
Summary: Transfer surface layers between Napari and Blender
Home-page: https://github.com/haesleinhuepf/napari-blender-bridge
Author: Robert Haase
Author-email: robert.haase@tu-dresden.de
License: GNU GPL v3.0
Classifier: Development Status :: 2 - Pre-Alpha
Classifier: Intended Audience :: Science/Research
Classifier: Framework :: napari
Classifier: Topic :: Scientific/Engineering :: Image Processing
Classifier: Programming Language :: Python
Classifier: Programming Language :: Python :: 3
Classifier: Programming Language :: Python :: 3.8
Classifier: Programming Language :: Python :: 3.9
Classifier: Operating System :: OS Independent
Classifier: License :: OSI Approved :: GNU General Public License v3 (GPLv3)
Requires-Python: >=3.8
License-File: LICENSE
Requires-Dist: napari-plugin-engine (>=0.1.4)
Requires-Dist: numpy
Requires-Dist: napari-tools-menu
Requires-Dist: napari-process-points-and-surfaces (>=0.4.2)
Requires-Dist: vedo
